dspbp.cp310-win_amd64.pyd
dspbp-0.1.1.dist-info/LICENSE
dspbp-0.1.1.dist-info/METADATA
dspbp-0.1.1.dist-info/WHEEL
dspbp-0.1.1.dist-info/top_level.txt
dspbp-0.1.1.dist-info/RECORD
