Metadata-Version: 2.1
Name: dspbp
Version: 0.1.1
Summary: Blueprint editing tools for Dyson Sphere Program
Home-page: https://github.com/Wesmania/dspbp
Author: Wesmania
Author-email: ikotrasinsk@gmail.com
License: License :: OSI Approved :: MIT License
Project-URL: Source, https://github.com/Wesmania/dspbp
Project-URL: Tracker, https://github.com/Wesmania/dspbp/issues
Platform: any
Classifier: License :: OSI Approved :: MIT License
Classifier: Programming Language :: Python :: 3.7
Classifier: Programming Language :: Python :: 3.8
Classifier: Programming Language :: Python :: 3.9
Classifier: Programming Language :: Python :: 3.10
Classifier: Operating System :: POSIX :: Linux
Classifier: Operating System :: Microsoft :: Windows
Requires-Python: >=3.7
License-File: LICENSE
